deltavar/__init__.py
deltavar/core.py
deltavar/sigma.py
deltavar/utils.py
deltavar-0.1.1.dist-info/licenses/LICENSE
deltavar-0.1.1.dist-info/METADATA
deltavar-0.1.1.dist-info/WHEEL
deltavar-0.1.1.dist-info/top_level.txt
deltavar-0.1.1.dist-info/RECORD
