Metadata-Version: 2.4
Name: deltavar
Version: 0.1.1
Summary: Tools to calculate the Delta Variance for epistemic uncertainty estimation in PyTorch, using torch.func.
Requires-Python: >=3.11
License-File: LICENSE
Requires-Dist: pytest>=8.3.5
Requires-Dist: torch>=2.3.1
Dynamic: license-file
